clapDetector/__init__.py
clapDetector/clapDetector.py
clap_detector-2.0.6.dist-info/LICENSE.txt
clap_detector-2.0.6.dist-info/METADATA
clap_detector-2.0.6.dist-info/WHEEL
clap_detector-2.0.6.dist-info/top_level.txt
clap_detector-2.0.6.dist-info/RECORD
