Metadata-Version: 2.1
Name: clap-detector
Version: 2.0.6
Summary: A clap detector that can detect claps in patterns of single, double, etc.
Home-page: https://github.com/TzurSoffer/clapDetection
Author: Tzur Soffer
Author-email: tzur.soffer@gmail.com
Classifier: Programming Language :: Python :: 3
Classifier: License :: OSI Approved :: MIT License
Classifier: Operating System :: OS Independent
License-File: LICENSE.txt
Requires-Dist: numpy
Requires-Dist: scipy
Requires-Dist: pyaudio
